plone.formwidget.geolocation-3.0.7-py3.11-nspkg.pth
plone/formwidget/geolocation/__init__.py
plone/formwidget/geolocation/configure.zcml
plone/formwidget/geolocation/controlpanel.py
plone/formwidget/geolocation/converter.py
plone/formwidget/geolocation/deserializer.py
plone/formwidget/geolocation/field.py
plone/formwidget/geolocation/geolocation.py
plone/formwidget/geolocation/geolocation_display.pt
plone/formwidget/geolocation/geolocation_input.pt
plone/formwidget/geolocation/interfaces.py
plone/formwidget/geolocation/popup.pt
plone/formwidget/geolocation/popup.py
plone/formwidget/geolocation/serializer.py
plone/formwidget/geolocation/setuphandlers.py
plone/formwidget/geolocation/supermodel.py
plone/formwidget/geolocation/testing.py
plone/formwidget/geolocation/testing.zcml
plone/formwidget/geolocation/upgrades.py
plone/formwidget/geolocation/upgrades.zcml
plone/formwidget/geolocation/vocabularies.py
plone/formwidget/geolocation/widget.py
plone/formwidget/geolocation/locales/plone.formwidget.geolocation.pot
plone/formwidget/geolocation/locales/update.sh
plone/formwidget/geolocation/locales/de/LC_MESSAGES/plone.formwidget.geolocation.po
plone/formwidget/geolocation/locales/fr/LC_MESSAGES/plone.formwidget.geolocation.po
plone/formwidget/geolocation/locales/nl/LC_MESSAGES/plone.formwidget.geolocation.po
plone/formwidget/geolocation/profiles/default/controlpanel.xml
plone/formwidget/geolocation/profiles/default/metadata.xml
plone/formwidget/geolocation/profiles/default/registry.xml
plone/formwidget/geolocation/profiles/uninstall/registry.xml
plone/formwidget/geolocation/profiles/upgrades/to_2000/registry.xml
plone/formwidget/geolocation/profiles/upgrades/to_2002/registry.xml
plone/formwidget/geolocation/static/151b708954e10ff9b542.png
plone/formwidget/geolocation/static/1551f4f60c37af51121f.woff2
plone/formwidget/geolocation/static/1f2cc17911c8d4a3fa01.png
plone/formwidget/geolocation/static/2285773e6b4b172f07d9.woff
plone.formwidget.geolocation-3.0.7.dist-info/METADATA
plone.formwidget.geolocation-3.0.7.dist-info/WHEEL
plone.formwidget.geolocation-3.0.7.dist-info/entry_points.txt
plone.formwidget.geolocation-3.0.7.dist-info/namespace_packages.txt
plone.formwidget.geolocation-3.0.7.dist-info/top_level.txt
plone.formwidget.geolocation-3.0.7.dist-info/RECORD
