Metadata-Version: 2.1
Name: plone.formwidget.geolocation
Version: 3.0.7
Summary: Geolocation field and widget
Home-page: https://github.com/collective/plone.formwidget.geolocation
Author: David Glick
Author-email: dglick@gmail.com
License: GPL
Keywords: z3c form leaflet map field widget
Classifier: Framework :: Plone
Classifier: Framework :: Plone :: 6.0
Classifier: Programming Language :: Python
Classifier: Programming Language :: Python :: 3.8
Classifier: Programming Language :: Python :: 3.9
Classifier: Programming Language :: Python :: 3.10
Classifier: Topic :: Software Development :: Libraries :: Python Modules
Classifier: Development Status :: 5 - Production/Stable
Classifier: License :: OSI Approved :: GNU General Public License v2 (GPLv2)
Requires-Python: >=3.8
Requires-Dist: setuptools
Requires-Dist: z3c.form
Requires-Dist: Products.CMFPlone >=6.0.0
Provides-Extra: test
Requires-Dist: plone.app.testing ; extra == 'test'
Requires-Dist: plone.restapi ; extra == 'test'
Requires-Dist: plone.testing ; extra == 'test'
Requires-Dist: mock ; extra == 'test'
